[
  {
    "stock_code": "017670",
    "corp_name": "SK텔레콤",
    "sector": "무선통신서비스",
    "return_5d": 12.16,
    "volume_ratio": 1.85,
    "health_score": 36.4,
    "total_score": 55.2
  },
  {
    "stock_code": "454910",
    "corp_name": "두산로보틱스",
    "sector": "기계",
    "return_5d": 1.35,
    "volume_ratio": 3.31,
    "health_score": 50.0,
    "total_score": 52.6
  },
  {
    "stock_code": "267270",
    "corp_name": "HD건설기계",
    "sector": "기계",
    "return_5d": 3.42,
    "volume_ratio": 0.93,
    "health_score": 50.0,
    "total_score": 51.2
  },
  {
    "stock_code": "032640",
    "corp_name": "LG유플러스",
    "sector": "무선통신서비스",
    "return_5d": 2.74,
    "volume_ratio": 0.62,
    "health_score": 59.0,
    "total_score": 48.8
  },
  {
    "stock_code": "241560",
    "corp_name": "두산밥캣",
    "sector": "기계",
    "return_5d": 0.79,
    "volume_ratio": 0.65,
    "health_score": 50.0,
    "total_score": 35.8
  }
]